{
  "indexes": [
    {
      "collectionGroup": "Subscriptions",
      "queryScope": "COLLECTION_GROUP",
      "fields": [
        {
          "fieldPath": "kolID",
          "order": "ASCENDING"
        },
        {
          "fieldPath": "status",
          "order": "ASCENDING"
        }
      ]
    },
    {
      "collectionGroup": "Subscriptions",
      "queryScope": "COLLECTION_GROUP",
      "fields": [
        {
          "fieldPath": "kolID",
          "order": "ASCENDING"
        },
        {
          "fieldPath": "deletedAt",
          "order": "ASCENDING"
        }
      ]
    },
    {
      "collectionGroup": "Subscriptions",
      "queryScope": "COLLECTION",
      "fields": [
        {
          "fieldPath": "xHandle",
          "order": "ASCENDING"
        },
        {
          "fieldPath": "deletedAt",
          "order": "ASCENDING"
        }
      ]
    },
    {
      "collectionGroup": "Subscriptions",
      "queryScope": "COLLECTION",
      "fields": [
        {
          "fieldPath": "deletedAt",
          "order": "ASCENDING"
        },
        {
          "fieldPath": "xHandle",
          "order": "ASCENDING"
        }
      ]
    },
    {
      "collectionGroup": "KOLs",
      "queryScope": "COLLECTION",
      "fields": [
        {
          "fieldPath": "xHandle",
          "order": "ASCENDING"
        },
        {
          "fieldPath": "deletedAt",
          "order": "ASCENDING"
        }
      ]
    }
  ],
  "fieldOverrides": [
    {
      "collectionGroup": "Users",
      "fieldPath": "telegramUserID",
      "indexes": [{
        "queryScope": "COLLECTION",
        "order": "ASCENDING"
      }]
    },
    {
      "collectionGroup": "APIKeys",
      "fieldPath": "hash",
      "indexes": [{
        "queryScope": "COLLECTION_GROUP",
        "order": "ASCENDING"
      }]
    },
    {
      "collectionGroup": "KOLs",
      "fieldPath": "xHandle",
      "indexes": [
        {
          "queryScope": "COLLECTION",
          "order": "ASCENDING"
        },
        {
          "queryScope": "COLLECTION",
          "arrayConfig": "CONTAINS"
        }
      ]
    },
    {
      "collectionGroup": "Subscriptions",
      "fieldPath": "kolID",
      "indexes": [
        {
          "queryScope": "COLLECTION_GROUP",
          "order": "ASCENDING"
        }, 
        {
          "queryScope": "COLLECTION_GROUP",
          "arrayConfig": "CONTAINS"
        }
      ]
    }
  ]
}